{
  "success": true,
  "meta": {
    "generatedAt": "2026-03-12T00:00:00Z",
    "account": "C (dimas.thomas.sancho@gmail.com)",
    "note": "5 active YouTube channels (2026-03-12). channelId auto-extracted from channel pages.",
    "verifiedAt": "2026-03-12"
  },
  "channels": {
    "philosopher": {
      "persona": "Philosopher-Parksy",
      "handle": "@philosopher-parksy",
      "channelId": "UCJaGuXjxoNjFMqfYUSFjZVg",
      "youtubeUrl": "https://www.youtube.com/@philosopher-parksy",
      "category": "category/Philosopher-Parksy/",
      "contentType": [
        "commentary",
        "framing",
        "concert",
        "experiment",
        "systems",
        "analytics"
      ],
      "siteUrl": "https://parksy.kr/channel/philosopher/",
      "subscribers": 0,
      "verified": true,
      "videos": [],
      "lastSynced": null,
      "absorbed": [
        "Tester-Parksy",
        "Protocol-Parksy",
        "Orbit-Log"
      ]
    },
    "blogger": {
      "persona": "Blogger-Parksy",
      "handle": "@blogger-parksy",
      "channelId": "UC5H8CnRGDxvx4v3HWrktuSg",
      "youtubeUrl": "https://www.youtube.com/@blogger-parksy",
      "category": "category/Blogger-Parksy/",
      "contentType": [
        "worldview",
        "essay",
        "narrative"
      ],
      "siteUrl": "https://parksy.kr/channel/blogger/",
      "subscribers": 0,
      "verified": true,
      "videos": [],
      "lastSynced": null
    },
    "visualizer": {
      "persona": "Visualizer-Parksy",
      "handle": "@visualizer-parksy",
      "channelId": "UC2MfUghTnMRE1xrODSfoELA",
      "youtubeUrl": "https://www.youtube.com/@visualizer-parksy",
      "category": "category/Visualizer-Parksy/",
      "contentType": [
        "webtoon",
        "image",
        "cad",
        "pipeline"
      ],
      "siteUrl": "https://parksy.kr/channel/visualizer/",
      "subscribers": 0,
      "verified": true,
      "videos": [],
      "lastSynced": null
    },
    "musician": {
      "persona": "Musician-Parksy",
      "handle": "@musician-parksy",
      "channelId": "UCun6b2HD3ekp35PhqbTfOlg",
      "youtubeUrl": "https://www.youtube.com/@musician-parksy",
      "category": "category/Musician-Parksy/",
      "contentType": [
        "bgm",
        "audio",
        "lyria3"
      ],
      "siteUrl": "https://parksy.kr/channel/musician/",
      "subscribers": 1,
      "verified": true,
      "videos": [],
      "lastSynced": null
    },
    "technician": {
      "persona": "Technician-Parksy",
      "handle": "@technician-parksy",
      "channelId": "UCfRaJjIn2oXyThHpAhOBSYg",
      "youtubeUrl": "https://www.youtube.com/@technician-parksy",
      "category": "category/Technician-Parksy/",
      "contentType": [
        "automation",
        "pipeline",
        "behind-the-scenes"
      ],
      "siteUrl": "https://parksy.kr/channel/technician/",
      "subscribers": 0,
      "verified": true,
      "videos": [],
      "lastSynced": null
    }
  },
  "deprecated": {
    "tester": {
      "note": "Tester-Parksy → Philosopher-Parksy로 통폐합 (2026-03-12). YouTube 채널 없음, 글 1개(테스트용)."
    },
    "protocol": {
      "note": "Protocol-Parksy → Philosopher-Parksy로 통폐합 (2026-03-12). YouTube 채널 없음, 글 4개."
    },
    "orbit": {
      "note": "Orbit-Log → Philosopher-Parksy로 통폐합 (2026-03-12). YouTube 채널 없음, 글 4개."
    }
  }
}